Multifunctionality/Multifunctionality.py
Multifunctionality/__init__.py
Multifunctionality-0.0.1.dist-info/METADATA
Multifunctionality-0.0.1.dist-info/WHEEL
Multifunctionality-0.0.1.dist-info/top_level.txt
Multifunctionality-0.0.1.dist-info/RECORD
