Metadata-Version: 2.1
Name: Multifunctionality
Version: 0.0.1
Summary: The number one package for utilities from a trustworthy source
Home-page: UNKNOWN
Author: Vihaan Mathur & Harihar Rengan
Author-email: vihaan.harihar341@gmail.com
License: UNKNOWN
Platform: UNKNOWN
Classifier: Programming Language :: Python :: 3
Classifier: License :: OSI Approved :: MIT License
Classifier: Operating System :: OS Independent
Requires-Python: >=3.6
Requires-Dist: keyboard
Requires-Dist: mouse
Requires-Dist: playsound (==1.2.2)
